{
    "version": "0.4",
    "title": "Contact Us",
    "type": "page",
    "metadata": {
        "template_type": "single-page",
        "include_in_zip": "1",
        "elementor_pro_required": "1",
        "wp_page_template": "elementor_header_footer"
    },
    "content": [
        {
            "id": "2984efaf",
            "settings": {
                "background_background": "classic",
                "background_image": {
                    "id": 124,
                    "url": "http:\/\/luxuryhotel.wpbuilt.co\/wp-content\/uploads\/sites\/7\/2020\/04\/luxury-hero-bg.jpg"
                },
                "background_position": "center center",
                "background_repeat": "no-repeat",
                "background_size": "cover",
                "slider_delay": "5000",
                "margin": {
                    "unit": "px",
                    "top": "-101",
                    "right": 0,
                    "bottom": "0",
                    "left": 0,
                    "isLinked": false
                },
                "custom_height_tablet": {
                    "unit": "px",
                    "size": 250,
                    "sizes": []
                },
                "custom_height_mobile": {
                    "unit": "px",
                    "size": 250,
                    "sizes": []
                },
                "padding": {
                    "unit": "px",
                    "top": "198",
                    "right": "0",
                    "bottom": "111",
                    "left": "0",
                    "isLinked": false
                },
                "padding_tablet": {
                    "unit": "px",
                    "top": "180",
                    "right": "0",
                    "bottom": "150",
                    "left": "0",
                    "isLinked": false
                },
                "custom_height": {
                    "unit": "px",
                    "size": 401,
                    "sizes": []
                },
                "margin_mobile": {
                    "unit": "px",
                    "top": "-110",
                    "right": 0,
                    "bottom": "0",
                    "left": 0,
                    "isLinked": false
                }
            },
            "elements": [
                {
                    "id": "269c0f37",
                    "settings": {
                        "_column_size": 100,
                        "_inline_size": null,
                        "slider_delay": "5000"
                    },
                    "elements": [
                        {
                            "id": "7bcc8600",
                            "settings": {
                                "title": "Contact Us",
                                "header_size": "h1",
                                "align": "center",
                                "title_color": "#FFFFFF",
                                "typography_typography": "custom",
                                "typography_font_family": "Georgia",
                                "typography_font_size": {
                                    "unit": "px",
                                    "size": 72,
                                    "sizes": []
                                },
                                "typography_font_size_tablet": {
                                    "unit": "px",
                                    "size": 55,
                                    "sizes": []
                                },
                                "typography_font_size_mobile": {
                                    "unit": "px",
                                    "size": 42,
                                    "sizes": []
                                },
                                "typography_font_weight": "normal"
                            },
                            "elements": [],
                            "isInner": false,
                            "widgetType": "heading",
                            "elType": "widget"
                        }
                    ],
                    "isInner": false,
                    "elType": "column"
                }
            ],
            "isInner": false,
            "elType": "section"
        },
        {
            "id": "64c8c252",
            "settings": {
                "structure": "20",
                "slider_delay": "5000",
                "padding": {
                    "unit": "px",
                    "top": "90",
                    "right": "0",
                    "bottom": "90",
                    "left": "0",
                    "isLinked": false
                },
                "padding_tablet": {
                    "unit": "px",
                    "top": "50",
                    "right": "0",
                    "bottom": "50",
                    "left": "0",
                    "isLinked": false
                },
                "content_width": {
                    "unit": "px",
                    "size": 1280,
                    "sizes": []
                }
            },
            "elements": [
                {
                    "id": "58df2f48",
                    "settings": {
                        "_column_size": 50,
                        "_inline_size": 55,
                        "slider_delay": "5000",
                        "_inline_size_tablet": 100,
                        "margin_tablet": {
                            "unit": "px",
                            "top": "0",
                            "right": "0",
                            "bottom": "30",
                            "left": "0",
                            "isLinked": false
                        }
                    },
                    "elements": [
                        {
                            "id": "209758d2",
                            "settings": {
                                "title": "Get in Touch",
                                "align": "left",
                                "title_color": "#000000",
                                "typography_typography": "custom",
                                "typography_font_family": "Georgia",
                                "typography_font_size": {
                                    "unit": "px",
                                    "size": 36,
                                    "sizes": []
                                },
                                "typography_font_size_tablet": {
                                    "unit": "px",
                                    "size": 27,
                                    "sizes": []
                                },
                                "typography_font_weight": "normal",
                                "align_mobile": "center"
                            },
                            "elements": [],
                            "isInner": false,
                            "widgetType": "heading",
                            "elType": "widget"
                        },
                        {
                            "id": "44c6fc53",
                            "settings": {
                                "title": "Lorem ipsum dolor sit amet, consectetur adipisicing elit, sed do eiusmod tempor incididunt ut labore et dolore magna aliqua. Ut enim ad minim veniam, quis nostrud exercitation ullamco laboris nisi ut aliquip",
                                "header_size": "p",
                                "title_color": "#999999",
                                "typography_typography": "custom",
                                "typography_font_family": "Lato",
                                "typography_font_size": {
                                    "unit": "px",
                                    "size": 18,
                                    "sizes": []
                                },
                                "typography_font_weight": "400",
                                "typography_line_height": {
                                    "unit": "em",
                                    "size": 1.7,
                                    "sizes": []
                                }
                            },
                            "elements": [],
                            "isInner": false,
                            "widgetType": "heading",
                            "elType": "widget"
                        },
                        {
                            "id": "7ccbc355",
                            "settings": {
                                "structure": "20",
                                "slider_delay": "5000",
                                "padding": {
                                    "unit": "px",
                                    "top": "0",
                                    "right": "0",
                                    "bottom": "20",
                                    "left": "0",
                                    "isLinked": false
                                }
                            },
                            "elements": [
                                {
                                    "id": "79796720",
                                    "settings": {
                                        "_column_size": 50,
                                        "_inline_size": null,
                                        "slider_delay": "5000",
                                        "padding": {
                                            "unit": "px",
                                            "top": "0",
                                            "right": "0",
                                            "bottom": "0",
                                            "left": "0",
                                            "isLinked": false
                                        },
                                        "padding_mobile": {
                                            "unit": "px",
                                            "top": "20",
                                            "right": "0",
                                            "bottom": "0",
                                            "left": "0",
                                            "isLinked": false
                                        }
                                    },
                                    "elements": [
                                        {
                                            "id": "3c50ec58",
                                            "settings": {
                                                "title": "Address",
                                                "header_size": "p",
                                                "title_color": "#B49C5C",
                                                "typography_typography": "custom",
                                                "typography_font_family": "Georgia",
                                                "typography_font_size": {
                                                    "unit": "px",
                                                    "size": 18,
                                                    "sizes": []
                                                },
                                                "typography_font_weight": "400",
                                                "align_mobile": "center"
                                            },
                                            "elements": [],
                                            "isInner": false,
                                            "widgetType": "heading",
                                            "elType": "widget"
                                        },
                                        {
                                            "id": "26910f9f",
                                            "settings": {
                                                "title": "East New York Brooklyn,\nNY, USA",
                                                "header_size": "h3",
                                                "title_color": "#999999",
                                                "typography_typography": "custom",
                                                "typography_font_size": {
                                                    "unit": "px",
                                                    "size": 24,
                                                    "sizes": []
                                                },
                                                "typography_font_weight": "400",
                                                "typography_line_height": {
                                                    "unit": "em",
                                                    "size": 1.5,
                                                    "sizes": []
                                                },
                                                "align_mobile": "center",
                                                "typography_font_size_mobile": {
                                                    "unit": "px",
                                                    "size": 22,
                                                    "sizes": []
                                                }
                                            },
                                            "elements": [],
                                            "isInner": false,
                                            "widgetType": "heading",
                                            "elType": "widget"
                                        }
                                    ],
                                    "isInner": true,
                                    "elType": "column"
                                },
                                {
                                    "id": "343e4d74",
                                    "settings": {
                                        "_column_size": 50,
                                        "_inline_size": null,
                                        "slider_delay": "5000",
                                        "padding": {
                                            "unit": "px",
                                            "top": "0",
                                            "right": "0",
                                            "bottom": "0",
                                            "left": "0",
                                            "isLinked": true
                                        },
                                        "margin_mobile": {
                                            "unit": "px",
                                            "top": "0",
                                            "right": "0",
                                            "bottom": "0",
                                            "left": "0",
                                            "isLinked": false
                                        },
                                        "padding_mobile": {
                                            "unit": "px",
                                            "top": "20",
                                            "right": "0",
                                            "bottom": "0",
                                            "left": "0",
                                            "isLinked": false
                                        }
                                    },
                                    "elements": [
                                        {
                                            "id": "12429f34",
                                            "settings": {
                                                "title": "Email Address",
                                                "header_size": "p",
                                                "title_color": "#B49C5C",
                                                "typography_typography": "custom",
                                                "typography_font_family": "Georgia",
                                                "typography_font_size": {
                                                    "unit": "px",
                                                    "size": 18,
                                                    "sizes": []
                                                },
                                                "typography_font_weight": "400",
                                                "align_mobile": "center"
                                            },
                                            "elements": [],
                                            "isInner": false,
                                            "widgetType": "heading",
                                            "elType": "widget"
                                        },
                                        {
                                            "id": "4a279c12",
                                            "settings": {
                                                "title": "hello@hotel.com",
                                                "header_size": "h3",
                                                "title_color": "#999999",
                                                "typography_typography": "custom",
                                                "typography_font_size": {
                                                    "unit": "px",
                                                    "size": 24,
                                                    "sizes": []
                                                },
                                                "typography_font_weight": "400",
                                                "typography_line_height": {
                                                    "unit": "em",
                                                    "size": 1.5,
                                                    "sizes": []
                                                },
                                                "align_mobile": "center",
                                                "typography_font_size_mobile": {
                                                    "unit": "px",
                                                    "size": 22,
                                                    "sizes": []
                                                }
                                            },
                                            "elements": [],
                                            "isInner": false,
                                            "widgetType": "heading",
                                            "elType": "widget"
                                        }
                                    ],
                                    "isInner": true,
                                    "elType": "column"
                                }
                            ],
                            "isInner": true,
                            "elType": "section"
                        },
                        {
                            "id": "3c3131c9",
                            "settings": {
                                "structure": "20",
                                "slider_delay": "5000"
                            },
                            "elements": [
                                {
                                    "id": "7aed15f4",
                                    "settings": {
                                        "_column_size": 50,
                                        "_inline_size": null,
                                        "slider_delay": "5000",
                                        "padding": {
                                            "unit": "px",
                                            "top": "0",
                                            "right": "0",
                                            "bottom": "0",
                                            "left": "0",
                                            "isLinked": false
                                        },
                                        "padding_mobile": {
                                            "unit": "px",
                                            "top": "20",
                                            "right": "0",
                                            "bottom": "0",
                                            "left": "0",
                                            "isLinked": false
                                        }
                                    },
                                    "elements": [
                                        {
                                            "id": "2dc9fa5b",
                                            "settings": {
                                                "title": "Phone Number",
                                                "header_size": "p",
                                                "title_color": "#B49C5C",
                                                "typography_typography": "custom",
                                                "typography_font_family": "Georgia",
                                                "typography_font_size": {
                                                    "unit": "px",
                                                    "size": 18,
                                                    "sizes": []
                                                },
                                                "typography_font_weight": "400",
                                                "align_mobile": "center"
                                            },
                                            "elements": [],
                                            "isInner": false,
                                            "widgetType": "heading",
                                            "elType": "widget"
                                        },
                                        {
                                            "id": "6bbe94e0",
                                            "settings": {
                                                "title": "+123 456 7890",
                                                "header_size": "h3",
                                                "title_color": "#999999",
                                                "typography_typography": "custom",
                                                "typography_font_size": {
                                                    "unit": "px",
                                                    "size": 24,
                                                    "sizes": []
                                                },
                                                "typography_font_weight": "400",
                                                "typography_line_height": {
                                                    "unit": "em",
                                                    "size": 1.5,
                                                    "sizes": []
                                                },
                                                "align_mobile": "center",
                                                "typography_font_size_mobile": {
                                                    "unit": "px",
                                                    "size": 22,
                                                    "sizes": []
                                                }
                                            },
                                            "elements": [],
                                            "isInner": false,
                                            "widgetType": "heading",
                                            "elType": "widget"
                                        }
                                    ],
                                    "isInner": true,
                                    "elType": "column"
                                },
                                {
                                    "id": "34b9982",
                                    "settings": {
                                        "_column_size": 50,
                                        "_inline_size": null,
                                        "slider_delay": "5000",
                                        "padding": {
                                            "unit": "px",
                                            "top": "0",
                                            "right": "0",
                                            "bottom": "0",
                                            "left": "0",
                                            "isLinked": true
                                        },
                                        "padding_mobile": {
                                            "unit": "px",
                                            "top": "20",
                                            "right": "0",
                                            "bottom": "0",
                                            "left": "0",
                                            "isLinked": false
                                        }
                                    },
                                    "elements": [
                                        {
                                            "id": "156a0083",
                                            "settings": {
                                                "title": "Contact With Us",
                                                "header_size": "p",
                                                "title_color": "#B49C5C",
                                                "typography_typography": "custom",
                                                "typography_font_family": "Georgia",
                                                "typography_font_size": {
                                                    "unit": "px",
                                                    "size": 18,
                                                    "sizes": []
                                                },
                                                "typography_font_weight": "400",
                                                "align_mobile": "center"
                                            },
                                            "elements": [],
                                            "isInner": false,
                                            "widgetType": "heading",
                                            "elType": "widget"
                                        },
                                        {
                                            "id": "6e8d3904",
                                            "settings": {
                                                "social_icon_list": [
                                                    {
                                                        "social_icon": {
                                                            "value": "fab fa-facebook-f",
                                                            "library": "fa-brands"
                                                        },
                                                        "_id": "d2c2881",
                                                        "link": {
                                                            "url": "",
                                                            "is_external": "true",
                                                            "nofollow": "",
                                                            "custom_attributes": ""
                                                        },
                                                        "item_icon_color": "default",
                                                        "item_icon_primary_color": "",
                                                        "item_icon_secondary_color": ""
                                                    },
                                                    {
                                                        "social_icon": {
                                                            "value": "fab fa-twitter",
                                                            "library": "fa-brands"
                                                        },
                                                        "_id": "6d5363a",
                                                        "link": {
                                                            "url": "",
                                                            "is_external": "true",
                                                            "nofollow": "",
                                                            "custom_attributes": ""
                                                        },
                                                        "item_icon_color": "default",
                                                        "item_icon_primary_color": "",
                                                        "item_icon_secondary_color": ""
                                                    },
                                                    {
                                                        "social_icon": {
                                                            "value": "fab fa-instagram",
                                                            "library": "fa-brands"
                                                        },
                                                        "_id": "36d4b31",
                                                        "link": {
                                                            "url": "",
                                                            "is_external": "true",
                                                            "nofollow": "",
                                                            "custom_attributes": ""
                                                        },
                                                        "item_icon_color": "default",
                                                        "item_icon_primary_color": "",
                                                        "item_icon_secondary_color": ""
                                                    },
                                                    {
                                                        "social_icon": {
                                                            "value": "fab fa-linkedin-in",
                                                            "library": "fa-brands"
                                                        },
                                                        "link": {
                                                            "url": "",
                                                            "is_external": "true",
                                                            "nofollow": "",
                                                            "custom_attributes": ""
                                                        },
                                                        "item_icon_color": "default",
                                                        "item_icon_primary_color": "",
                                                        "item_icon_secondary_color": "",
                                                        "_id": "ef7d902"
                                                    }
                                                ],
                                                "align": "left",
                                                "icon_color": "custom",
                                                "icon_primary_color": "rgba(0, 0, 0, 0)",
                                                "icon_secondary_color": "#999999",
                                                "align_mobile": "center",
                                                "hover_secondary_color": "#B49C5C"
                                            },
                                            "elements": [],
                                            "isInner": false,
                                            "widgetType": "social-icons",
                                            "elType": "widget"
                                        }
                                    ],
                                    "isInner": true,
                                    "elType": "column"
                                }
                            ],
                            "isInner": true,
                            "elType": "section"
                        }
                    ],
                    "isInner": false,
                    "elType": "column"
                },
                {
                    "id": "7db1d149",
                    "settings": {
                        "_column_size": 50,
                        "_inline_size": 44.923,
                        "slider_delay": "5000",
                        "_inline_size_tablet": 100
                    },
                    "elements": [
                        {
                            "id": "13e0f6be",
                            "settings": {
                                "form_name": "New Form",
                                "form_fields": [
                                    {
                                        "custom_id": "name",
                                        "field_type": "text",
                                        "field_label": "Name",
                                        "placeholder": "Name",
                                        "width": "100",
                                        "_id": "c87c26a",
                                        "required": "true",
                                        "field_options": "",
                                        "allow_multiple": "",
                                        "select_size": "",
                                        "inline_list": "",
                                        "field_html": "",
                                        "width_tablet": "",
                                        "width_mobile": "",
                                        "rows": 4,
                                        "recaptcha_size": "normal",
                                        "recaptcha_style": "light",
                                        "recaptcha_badge": "bottomright",
                                        "css_classes": "",
                                        "field_value": "",
                                        "file_sizes": "",
                                        "file_types": "",
                                        "allow_multiple_upload": "",
                                        "max_files": "",
                                        "acceptance_text": "",
                                        "checked_by_default": "",
                                        "field_min": "",
                                        "field_max": "",
                                        "min_date": "",
                                        "max_date": "",
                                        "use_native_date": "",
                                        "use_native_time": ""
                                    },
                                    {
                                        "custom_id": "email",
                                        "field_type": "email",
                                        "required": "true",
                                        "field_label": "Email",
                                        "placeholder": "Email",
                                        "width": "100",
                                        "_id": "2609b95",
                                        "field_options": "",
                                        "allow_multiple": "",
                                        "select_size": "",
                                        "inline_list": "",
                                        "field_html": "",
                                        "width_tablet": "",
                                        "width_mobile": "",
                                        "rows": 4,
                                        "recaptcha_size": "normal",
                                        "recaptcha_style": "light",
                                        "recaptcha_badge": "bottomright",
                                        "css_classes": "",
                                        "field_value": "",
                                        "file_sizes": "",
                                        "file_types": "",
                                        "allow_multiple_upload": "",
                                        "max_files": "",
                                        "acceptance_text": "",
                                        "checked_by_default": "",
                                        "field_min": "",
                                        "field_max": "",
                                        "min_date": "",
                                        "max_date": "",
                                        "use_native_date": "",
                                        "use_native_time": ""
                                    },
                                    {
                                        "field_type": "text",
                                        "field_label": "Phone Number",
                                        "placeholder": "Phone Number",
                                        "required": "true",
                                        "field_options": "",
                                        "allow_multiple": "",
                                        "select_size": "",
                                        "inline_list": "",
                                        "field_html": "",
                                        "width": "100",
                                        "width_tablet": "",
                                        "width_mobile": "",
                                        "rows": 4,
                                        "recaptcha_size": "normal",
                                        "recaptcha_style": "light",
                                        "recaptcha_badge": "bottomright",
                                        "css_classes": "",
                                        "field_value": "",
                                        "custom_id": "field_9b4576c",
                                        "_id": "9b4576c",
                                        "file_sizes": "",
                                        "file_types": "",
                                        "allow_multiple_upload": "",
                                        "max_files": "",
                                        "acceptance_text": "",
                                        "checked_by_default": "",
                                        "field_min": "",
                                        "field_max": "",
                                        "min_date": "",
                                        "max_date": "",
                                        "use_native_date": "",
                                        "use_native_time": ""
                                    },
                                    {
                                        "custom_id": "message",
                                        "field_type": "textarea",
                                        "field_label": "Message",
                                        "placeholder": "Message",
                                        "width": "100",
                                        "_id": "d8f4ec6",
                                        "required": "",
                                        "field_options": "",
                                        "allow_multiple": "",
                                        "select_size": "",
                                        "inline_list": "",
                                        "field_html": "",
                                        "width_tablet": "",
                                        "width_mobile": "",
                                        "rows": 6,
                                        "recaptcha_size": "normal",
                                        "recaptcha_style": "light",
                                        "recaptcha_badge": "bottomright",
                                        "css_classes": "",
                                        "field_value": "",
                                        "file_sizes": "",
                                        "file_types": "",
                                        "allow_multiple_upload": "",
                                        "max_files": "",
                                        "acceptance_text": "",
                                        "checked_by_default": "",
                                        "field_min": "",
                                        "field_max": "",
                                        "min_date": "",
                                        "max_date": "",
                                        "use_native_date": "",
                                        "use_native_time": ""
                                    }
                                ],
                                "input_size": "lg",
                                "show_labels": "",
                                "button_text": "Send a Message",
                                "button_align": "end",
                                "email_content": "[all-fields]",
                                "email_content_2": "[all-fields]",
                                "success_message": "The form was sent successfully.",
                                "error_message": "An error occured.",
                                "required_field_message": "This field is required.",
                                "invalid_message": "There's something wrong. The form is invalid.",
                                "field_typography_typography": "custom",
                                "field_typography_font_family": "Lato",
                                "field_typography_font_size": {
                                    "unit": "px",
                                    "size": 18,
                                    "sizes": []
                                },
                                "field_background_color": "#FFFFFF",
                                "field_border_color": "#EBEBEB",
                                "field_border_radius": {
                                    "unit": "px",
                                    "top": "0",
                                    "right": "0",
                                    "bottom": "0",
                                    "left": "0",
                                    "isLinked": false
                                },
                                "button_background_color": "#B49C5C",
                                "button_typography_typography": "custom",
                                "button_typography_font_family": "Lato",
                                "button_typography_font_size": {
                                    "unit": "px",
                                    "size": 18,
                                    "sizes": []
                                },
                                "button_typography_font_weight": "600",
                                "button_typography_text_transform": "none",
                                "button_typography_letter_spacing": {
                                    "unit": "px",
                                    "size": 0,
                                    "sizes": []
                                },
                                "button_border_radius": {
                                    "unit": "px",
                                    "top": "0",
                                    "right": "0",
                                    "bottom": "0",
                                    "left": "0",
                                    "isLinked": true
                                },
                                "button_text_padding": {
                                    "unit": "px",
                                    "top": "20",
                                    "right": "30",
                                    "bottom": "20",
                                    "left": "30",
                                    "isLinked": false
                                },
                                "button_align_tablet": "stretch",
                                "button_border_border": "solid",
                                "button_border_width": {
                                    "unit": "px",
                                    "top": "1",
                                    "right": "1",
                                    "bottom": "1",
                                    "left": "1",
                                    "isLinked": true
                                },
                                "button_border_color": "#B49C5C",
                                "button_background_hover_color": "rgba(0, 0, 0, 0)",
                                "button_hover_color": "#B49C5C",
                                "button_hover_border_color": "#B49C5C"
                            },
                            "elements": [],
                            "isInner": false,
                            "widgetType": "form",
                            "elType": "widget"
                        }
                    ],
                    "isInner": false,
                    "elType": "column"
                }
            ],
            "isInner": false,
            "elType": "section"
        },
        {
            "id": "3f3d71aa",
            "settings": {
                "slider_delay": "5000",
                "padding": {
                    "unit": "px",
                    "top": "0",
                    "right": "0",
                    "bottom": "50",
                    "left": "0",
                    "isLinked": false
                },
                "content_width": {
                    "unit": "px",
                    "size": 1280,
                    "sizes": []
                },
                "background_background": "classic",
                "background_image": {
                    "id": 38,
                    "url": "http:\/\/luxuryhotel.wpbuilt.co\/wp-content\/uploads\/sites\/7\/2020\/04\/luxuarious-bg.png"
                },
                "background_position": "center center",
                "background_repeat": "no-repeat"
            },
            "elements": [
                {
                    "id": "6ca64e9d",
                    "settings": {
                        "_column_size": 100,
                        "_inline_size": null,
                        "slider_delay": "5000",
                        "padding": {
                            "unit": "px",
                            "top": "20",
                            "right": "0",
                            "bottom": "20",
                            "left": "0",
                            "isLinked": false
                        }
                    },
                    "elements": [
                        {
                            "id": "66c7a28",
                            "settings": {
                                "address": "London Eye, London, United Kingdom",
                                "zoom": {
                                    "unit": "px",
                                    "size": 15,
                                    "sizes": []
                                },
                                "height": {
                                    "unit": "px",
                                    "size": 455,
                                    "sizes": []
                                },
                                "css_filters_css_filter": "custom",
                                "css_filters_brightness": {
                                    "unit": "px",
                                    "size": 79,
                                    "sizes": []
                                },
                                "css_filters_contrast": {
                                    "unit": "px",
                                    "size": 139,
                                    "sizes": []
                                },
                                "css_filters_saturate": {
                                    "unit": "px",
                                    "size": 0,
                                    "sizes": []
                                }
                            },
                            "elements": [],
                            "isInner": false,
                            "widgetType": "google_maps",
                            "elType": "widget"
                        }
                    ],
                    "isInner": false,
                    "elType": "column"
                }
            ],
            "isInner": false,
            "elType": "section"
        }
    ],
    "page_settings": {
        "custom_css": ".gc-walkthrough .swiper-slide.swiper-slide-next {\r\n    width: 45% !important;\r\n}\r\n\r\n.gc-walkthrough .swiper-slide-active[data-swiper-slide-index=\"0\"] {\r\n    margin-left: -10% !important;\r\n}\r\n\r\n\r\n.gc-walkthrough .swiper-slide-active {\r\n    margin-left: -22%;\r\n    width: 40% !important;\r\n}\r\n\r\n\r\n.swiper-slide.swiper-slide-duplicate-prev {\r\n    width: 40% !important;\r\n}\r\n\r\n\r\n\r\n.gc-home-gallery .elementor-image-carousel-wrapper:before {\r\n    position: absolute;\r\n    background: #fff;\r\n    content: '';\r\n    width: 275px;\r\n    bottom: 0;\r\n    left: 0;\r\n    z-index: 9;\r\n    height: 80px;\r\n}\r\n\r\n.gc-home-gallery .elementor-image-carousel-wrapper:after {\r\n    position: absolute;\r\n    background: #fff;\r\n    content: '';\r\n    width: 262px;\r\n    top: 0;\r\n    right: 0;\r\n    z-index: 9;\r\n    height: 80px;\r\n}\r\n\r\n.gc-home-gallery {\r\n    position: relative !important;\r\n}\r\n\r\n.gc-home-gallery .elementor-swiper-button-prev, .gc-home-gallery  .elementor-swiper-button-next {\r\n    top: unset;\r\n    color: #000;\r\n    bottom: 2.5%;\r\n    left: 33%;\r\n    z-index: 999;\r\n    transform: translate(15%, -50%);\r\n}",
        "template": "elementor_header_footer"
    }
}